scikit_radiomics-1.0.0.dist-info/DESCRIPTION.rst
scikit_radiomics-1.0.0.dist-info/METADATA
scikit_radiomics-1.0.0.dist-info/RECORD
scikit_radiomics-1.0.0.dist-info/WHEEL
scikit_radiomics-1.0.0.dist-info/metadata.json
scikit_radiomics-1.0.0.dist-info/top_level.txt
skradiomics/__init__.py
skradiomics/version.py
skradiomics/feature_extraction/__init__.py
skradiomics/feature_extraction/base.py
skradiomics/feature_extraction/feature_extractor.py
skradiomics/feature_extraction/firstorder.py
skradiomics/feature_extraction/glcm.py
skradiomics/feature_extraction/gldm.py
skradiomics/feature_extraction/glrlm.py
skradiomics/feature_extraction/glszm.py
skradiomics/feature_extraction/ngtdm.py
skradiomics/feature_extraction/shape.py
skradiomics/feature_selection/ANOVA.py
skradiomics/feature_selection/Fisher.py
skradiomics/feature_selection/Information.py
skradiomics/feature_selection/Relief.py
skradiomics/feature_selection/T_test.py
skradiomics/feature_selection/Wilcoxon.py
skradiomics/feature_selection/__init__.py
skradiomics/feature_selection/mRMR.py
skradiomics/feature_selection/utils.py
skradiomics/metrics/CCC.py
skradiomics/metrics/ICC.py
skradiomics/metrics/__init__.py
skradiomics/metrics/score.py
skradiomics/metrics/utils.py
skradiomics/preprocessing/__init__.py
skradiomics/preprocessing/image_filter.py
skradiomics/preprocessing/image_process.py
skradiomics/preprocessing/image_regular.py
skradiomics/utils/__init__.py
skradiomics/utils/modules.py
skradiomics/utils/registry.py
skradiomics/utils/schema_functions.py
skradiomics/utils/schema_params.yaml
